pyfujitsu/__init__.py
pyfujitsu/api.py
pyfujitsu/splitAC.py
pyfujitsu-0.8.1.1.dist-info/LICENSE
pyfujitsu-0.8.1.1.dist-info/METADATA
pyfujitsu-0.8.1.1.dist-info/WHEEL
pyfujitsu-0.8.1.1.dist-info/top_level.txt
pyfujitsu-0.8.1.1.dist-info/RECORD
