Metadata-Version: 2.1
Name: pyfujitsu
Version: 0.8.1.1
Summary: Python library to control Fujitsu General Airconditioners on AylaNetworks IoT platform
Home-page: https://github.com/Mmodarre/pyfujitsu
Author: Mehdi Modarressi
Author-email: Luckposht@gmail.com
License: UNKNOWN
Platform: UNKNOWN
Classifier: Programming Language :: Python :: 3
Classifier: License :: OSI Approved :: MIT License
Classifier: Operating System :: OS Independent
Requires-Dist: certifi
Requires-Dist: chardet
Requires-Dist: idna
Requires-Dist: requests
Requires-Dist: urllib3
